vbump/__init__.py
vbump/__main__.py
vbump/__version__.py
vbump-1.2.0.dist-info/METADATA
vbump-1.2.0.dist-info/WHEEL
vbump-1.2.0.dist-info/entry_points.txt
vbump-1.2.0.dist-info/top_level.txt
vbump-1.2.0.dist-info/RECORD
