Metadata-Version: 2.1
Name: vbump
Version: 1.2.0
Summary: yet another python package version bump tool
Home-page: https://github.com/jkwill87/vbump
Author: Jessy Williams
Author-email: jessy@jessywilliams.com
License: MIT
Platform: UNKNOWN
